biometrics/VERSION
biometrics/__init__.py
biometrics/biometrics.py
biometrics/cli.py
biometrics/cluster.py
biometrics/extract.py
biometrics/genotype.py
biometrics/major_contamination.py
biometrics/minor_contamination.py
biometrics/sample.py
biometrics/sex_mismatch.py
biometrics/utils.py
biometrics-0.2.15.dist-info/AUTHORS.rst
biometrics-0.2.15.dist-info/LICENSE
biometrics-0.2.15.dist-info/METADATA
biometrics-0.2.15.dist-info/WHEEL
biometrics-0.2.15.dist-info/entry_points.txt
biometrics-0.2.15.dist-info/top_level.txt
biometrics-0.2.15.dist-info/RECORD
