Metadata-Version: 2.1
Name: biometrics
Version: 0.2.15
Summary: Package to generate sample based biometrics.
Home-page: https://github.com/msk-access/biometrics
Author: Charlie Murphy
Author-email: murphyc4@mskcc.org
License: Apache Software License 2.0
Keywords: biometrics
Classifier: Development Status :: 4 - Beta
Classifier: Intended Audience :: Developers
Classifier: License :: OSI Approved :: Apache Software License
Classifier: Natural Language :: English
Classifier: Programming Language :: Python :: 3
Classifier: Programming Language :: Python :: 3.5
Classifier: Programming Language :: Python :: 3.6
Classifier: Programming Language :: Python :: 3.7
Classifier: Programming Language :: Python :: 3.8
Classifier: Programming Language :: Python :: 3.9
Requires-Python: >=3.5
License-File: LICENSE
License-File: AUTHORS.rst
Requires-Dist: networkx
Requires-Dist: numpy
Requires-Dist: pandas
Requires-Dist: plotly
Requires-Dist: pysam
Requires-Dist: pyvcf3
Requires-Dist: python-dateutil
Requires-Dist: pytz
Requires-Dist: retrying
Requires-Dist: six
